{
  "MainUpgradePath": [
    {
      "ID": "Weapon_Laser_SmallLaserER_0-STOCK",
      "Weight": 100,
      "RandomLimit": 0.0,
      "MinDate": "0001-01-01T00:00:00",
      "ListLink": false,
      "AllowDowngrade": true
    },
    {
      "ID": "Weapon_Laser_SmallLaserER_1-Diverse_Optics",
      "Weight": 20,
      "RandomLimit": 0.0,
      "MinDate": "0001-01-01T00:00:00",
      "ListLink": false,
      "AllowDowngrade": false
    },
    {
      "ID": "Weapon_Laser_SmallLaserER_2-BlazeFire",
      "Weight": 5,
      "RandomLimit": 0.0,
      "MinDate": "0001-01-01T00:00:00",
      "ListLink": false,
      "AllowDowngrade": false
    }
  ],
  "AmmoTypes": [],
  "Addons": []
}