{
    "TargetID": "chassisdef_mongoose_MON-66b",
    "Instructions": [
        {
            "JSONPath": "$.FixedEquipment",
            "Action": "ArrayAdd",
			"Value": {
				"MountedLocation" : "LeftTorso",
				"ComponentDefID" : "Gear_SensorCAC_Beagle",
				"SimGameUID" : "",
				"ComponentDefType" : "Upgrade",
				"HardpointSlot" : -1,
				"IsFixed" : true,
				"GUID" : null,
				"DamageLevel" : "Functional",
				"prefabName" : null,
				"hasPrefabName" : false
			}
        },
		{
            "JSONPath": "$.FixedEquipment[?(@ComponentDefID == 'Gear_Sensor_ActiveProbe')]",
            "Action": "Remove"
        }
    ]
}